creadoc/__init__.py
creadoc/api.py
creadoc/app_meta.py
creadoc/controller.py
creadoc/models.py
creadoc/designer/__init__.py
creadoc/designer/actions.py
creadoc/designer/exceptions.py
creadoc/designer/forms.py
creadoc/designer/helpers.py
creadoc/designer/mutex.py
creadoc/docs/variable.txt
creadoc/docs/variable_types.txt
creadoc/migrations/0001_initial.py
creadoc/migrations/__init__.py
creadoc/report/__init__.py
creadoc/report/actions.py
creadoc/report/constants.py
creadoc/report/enums.py
creadoc/report/exceptions.py
creadoc/report/helpers.py
creadoc/report/registry.py
creadoc/report/source.py
creadoc/report/variable.py
creadoc/static/css/demo.css
creadoc/static/css/stimulsoft.designer.office2013.white.blue.css
creadoc/static/css/stimulsoft.viewer.office2013.css
creadoc/static/images/HighlightCondition.png
creadoc/static/images/Images.png
creadoc/static/images/Js.png
creadoc/static/images/JsBack.png
creadoc/static/images/MasterDetail.png
creadoc/static/images/MultiColumnList.png
creadoc/static/images/OnlineStoreSales.png
creadoc/static/images/ParametersSelectingCountry.png
creadoc/static/images/SimpleGroup.png
creadoc/static/images/SimpleList.png
creadoc/static/images/SiteStatistics.png
creadoc/static/images/SmartphoneBestsellersInQ12015.png
creadoc/static/images/StimulsoftReports.png
creadoc/static/images/UsersAppleIpad.png
creadoc/static/images/favicon.ico
creadoc/static/local/ru.ext.xml
creadoc/static/local/ru.xml
creadoc/static/reports/EmptyReport.mrt
creadoc/static/scripts/jquery-1.12.1.min.js
creadoc/static/scripts/stimulsoft.designer.js
creadoc/static/scripts/stimulsoft.reports.js
creadoc/static/scripts/stimulsoft.viewer.js
creadoc/templates/designer.html
creadoc/templates/viewer.html
creadoc/templates/viewer_background.html
creadoc/templates/scripts/DesignerDataSourcesWindow.js
creadoc/templates/scripts/DesignerIframeWindow.js
creadoc/templates/scripts/DesignerImportWindow.js
creadoc/templates/scripts/DesignerReportsListWindow.js
creadoc/viewer/__init__.py
creadoc-0.0.9.dist-info/METADATA
creadoc-0.0.9.dist-info/WHEEL
creadoc-0.0.9.dist-info/top_level.txt
creadoc-0.0.9.dist-info/RECORD
